uclip/__init__.py
uclip/compat.py
uclip/config.py
uclip/main.py
uclip/progress.py
uclip/uploader.py
uclip-0.1.4.dist-info/entry_points.txt
uclip-0.1.4.dist-info/LICENSE
uclip-0.1.4.dist-info/WHEEL
uclip-0.1.4.dist-info/METADATA
uclip-0.1.4.dist-info/RECORD
