Metadata-Version: 2.1
Name: uclip
Version: 0.1.4
Summary: Command Line Utility to upload clipboard images to B2 buckets
Home-page: https://github.com/ionite34/uclip
License: MIT
Keywords: upload,image,b2,clipboard
Author: ionite34
Author-email: dev@ionite.io
Requires-Python: >=3.7.2,<3.12
Classifier: License :: OSI Approved :: MIT License
Classifier: Programming Language :: Python :: 3
Classifier: Programming Language :: Python :: 3.10
Classifier: Programming Language :: Python :: 3.8
Classifier: Programming Language :: Python :: 3.9
Classifier: Topic :: Scientific/Engineering :: Image Processing
Classifier: Topic :: System :: Networking
Classifier: Topic :: Utilities
Requires-Dist: Pillow (>=9.1.1,<10.0.0)
Requires-Dist: b2sdk (>=1.18.0,<2.0.0)
Requires-Dist: backports.cached-property (>=1.0.2,<2.0.0); python_version < "3.8"
Requires-Dist: click (>=8.1.3,<9.0.0)
Requires-Dist: inquirerpy (>=0.3.4,<0.4.0)
Requires-Dist: keyring (>=23.9.3,<24.0.0)
Requires-Dist: pyperclip (>=1.8.2,<2.0.0)
Requires-Dist: rich (>=12.6.0,<13.0.0)
Requires-Dist: typing-extensions (>=4.4.0,<5.0.0)
Requires-Dist: yaspin (>=2.2.0,<3.0.0)
Project-URL: Repository, https://github.com/ionite34/uclip
